rcclab_gui/__init__.py
rcclab_gui/__main__.py
rcclab_gui/rcclab_gui.py
rcclab_gui-0.0.10.dist-info/LICENCE
rcclab_gui-0.0.10.dist-info/METADATA
rcclab_gui-0.0.10.dist-info/WHEEL
rcclab_gui-0.0.10.dist-info/entry_points.txt
rcclab_gui-0.0.10.dist-info/top_level.txt
rcclab_gui-0.0.10.dist-info/RECORD
