Metadata-Version: 2.1
Name: rcclab-gui
Version: 0.0.10
Summary: Primer intento de subir algo a PyPI
Home-page: https://github.com/RosarioCCLab/GUI
Author: Bruno A. Franco
Author-email: rosariocclab@gmail.com
License: MIT
Keywords: Graphical User Interface
Classifier: Programming Language :: Python :: 3
Classifier: License :: OSI Approved :: MIT License
Classifier: Operating System :: OS Independent
License-File: LICENCE
Requires-Dist: tk
Requires-Dist: pandas
Requires-Dist: numpy
Requires-Dist: openpyxl
